setup.py
sentry_s3_nodestore/__init__.py
sentry_s3_nodestore/backend.py
sentry_s3_nodestore.egg-info/PKG-INFO
sentry_s3_nodestore.egg-info/SOURCES.txt
sentry_s3_nodestore.egg-info/dependency_links.txt
sentry_s3_nodestore.egg-info/not-zip-safe
sentry_s3_nodestore.egg-info/requires.txt
sentry_s3_nodestore.egg-info/top_level.txt