Metadata-Version: 1.1
Name: sentry-s3-nodestore
Version: 1.0.0
Summary: A Sentry extension to add S3 as a NodeStore backend.
Home-page: http://github.com/ewdurbin/sentry-s3-nodestore
Author: Ernest W. Durbin III
Author-email: ewdurbin@gmail.com
License: BSD
Download-URL: https://pypi.python.org/pypi/sentry-s3-nodestore
Platform: UNKNOWN
Classifier: Framework :: Django
Classifier: Intended Audience :: Developers
Classifier: Intended Audience :: System Administrators
Classifier: Operating System :: OS Independent
Classifier: Topic :: Software Development
